Metadata-Version: 1.1
Name: generatecube
Version: 0.1.2
Summary: create scripts to launch gcubegen09d for each orbital independently to a gridengine queue
Home-page: UNKNOWN
Author: Davide Olianas
Author-email: ubuntupk@gmail.com
License: UNKNOWN
Platform: UNKNOWN
Requires: pystache
